mathscal/__init__.py
mathscal/mathscal.py
mathscal-0.1.3.dist-info/METADATA
mathscal-0.1.3.dist-info/WHEEL
mathscal-0.1.3.dist-info/top_level.txt
mathscal-0.1.3.dist-info/RECORD
