Metadata-Version: 2.1
Name: mathscal
Version: 0.1.3
Summary: Package to do maths
Home-page: UNKNOWN
Author: Aayam Shrestha
Author-email: aayamthebest555@gmail.com
License: UNKNOWN
Keywords: python,math calculation,mathscal,mathscal python,mathscal python by aayam,math calculation by aayam
Platform: UNKNOWN
Classifier: Development Status :: 1 - Planning
Classifier: Intended Audience :: Developers
Classifier: Programming Language :: Python :: 3
Classifier: Operating System :: Unix
Classifier: Operating System :: MacOS :: MacOS X
Classifier: Operating System :: Microsoft :: Windows
